scMMT/Preprocessing.py
scMMT/Utils.py
scMMT/__init__.py
scMMT/scMMT_API.py
scMMT/Data_Infrastructure/DataLoader.py
scMMT/Data_Infrastructure/DataLoader_Constructor.py
scMMT/Data_Infrastructure/Samplers.py
scMMT/Data_Infrastructure/__init__.py
scMMT/Network/Layers.py
scMMT/Network/Losses.py
scMMT/Network/Model.py
scMMT/Network/__init__.py
scMMT-1.0.1.dist-info/LICENSE
scMMT-1.0.1.dist-info/METADATA
scMMT-1.0.1.dist-info/WHEEL
scMMT-1.0.1.dist-info/top_level.txt
scMMT-1.0.1.dist-info/RECORD
