Metadata-Version: 2.1
Name: scMMT
Version: 1.0.1
Summary: A package for cell annotation, protein prediction, and low dimensional embedding representation
Home-page: https://github.com/SongqiZhou/scMMT
Author: Songqi Zhou
Author-email: zhousongqi21@gmail.com
Classifier: Programming Language :: Python :: 3
Classifier: License :: OSI Approved :: MIT License
Classifier: Operating System :: OS Independent
Requires-Python: >=3.10
License-File: LICENSE
Requires-Dist: torch (>=2.0.0)
Requires-Dist: scanpy (>=1.9.3)
Requires-Dist: scikit-learn (>=1.2.2)
Requires-Dist: scikit-learn-intelex (>=2023.1.1)
Requires-Dist: pandas (>=2.0.1)
Requires-Dist: numpy (>=1.24.3)
Requires-Dist: scipy (>=1.10.1)
Requires-Dist: tqdm (>=4.65.0)
Requires-Dist: anndata (>=0.9.1)
